setup.py
Xconnector/All_in_DB.py
Xconnector/Documentation.pdf
Xconnector/HMDB.py
Xconnector/ID_converter.py
Xconnector/KEGG.py
Xconnector/LMDB.py
Xconnector/SMPDB.py
Xconnector/T3DP.py
Xconnector/Xconnector.py
Xconnector/YMDB.py
Xconnector/__init__.py
Xconnector/deleted_codes.py
Xconnector/get_data_plot.py
Xconnector/logo.v1.ico
Xconnector/other_functions.py
Xconnector/plotDB.py
Xconnector/respectDB.py
Xconnector.egg-info/PKG-INFO
Xconnector.egg-info/SOURCES.txt
Xconnector.egg-info/dependency_links.txt
Xconnector.egg-info/requires.txt
Xconnector.egg-info/top_level.txt
Xconnector/logo/HMDB.png
Xconnector/logo/IM1.png
Xconnector/logo/IM2.png
Xconnector/logo/IM3.png
Xconnector/logo/IM4.png
Xconnector/logo/LMDB.png
Xconnector/logo/ReSpect.png
Xconnector/logo/T3DB.png
Xconnector/logo/YMDB.png
Xconnector/logo/__init__.py
Xconnector/logo/logo.v1.ico
Xconnector/logo/logo.v1.png
Xconnector/temp_files/__init__.py
Xconnector/temp_files/kegg.txt
Xconnector/temp_files/kegg_new.txt